{
    "mybean_mc": ""
    ,
    "mybean_bz": ""
    ,
    "package_bean": "wx.web.base.bean"
    ,
    "package_soo": "wx.web.base.soo"
    ,
    "name_soo": "<?c>Soo"
    ,
    "package_service": "wx.web.base.service"
    ,
    "name_service": "<?c>Service"
    ,
    "package_hm": "wx.web.base.hm.<?c>"
    ,
    "name_hmA": "<?c>ADU"
    ,
    "name_hmD": "<?c>ADU"
    ,
    "name_hmU": "<?c>ADU"
    ,
    "name_hmS": "<?c>S"
    ,
    "package_validate": "wx.web.base.hm.<?c>.validate"
    ,
    "name_validate": "<?c>Validate"
    ,
    "package_cache": "wx.web.base.hm.<?c>.cache"
    ,
    "name_cache": "<?c>Cache"
    ,
    "package_vo": "wx.web.base.hm.<?c>.vo"
    ,
    "name_vo": "<?c>VO"
    ,
    "vpackage_admin": "admin.base.<?c1>"
    ,
    "vname_adminA": "<?c1>_A"
    ,
    "vname_adminD": "<?c1>"
    ,
    "vname_adminS": "<?c1>"
    ,
    "vname_adminU": "<?c1>_U"
    ,
    "vpackage_admin_js": "admin.base.<?c1>.js"
    ,
    "vname_admin_js": "<?c1>"
    ,
    "vpackage_admin_css": "admin.base.<?c1>.css"
    ,
    "vname_admin_css": "<?c1>"
    ,
    "power_code": ""
    ,
    "power_codeA": "<?p>A"
    ,
    "power_codeD": "<?p>D"
    ,
    "power_codeS": "<?p>S"
    ,
    "power_codeU": "<?p>U"
}